bootstrap_py/__init__.py
bootstrap_py/classifiers.py
bootstrap_py/commands.py
bootstrap_py/control.py
bootstrap_py/docs.py
bootstrap_py/exceptions.py
bootstrap_py/package.py
bootstrap_py/pypi.py
bootstrap_py/update.py
bootstrap_py/vcs.py
bootstrap_py/version.py
bootstrap_py/data/classifiers.txt
bootstrap_py/data/classifiers.txt.sha256
bootstrap_py/templates/.coveragerc.j2
bootstrap_py/templates/.gitignore.j2
bootstrap_py/templates/MANIFEST.in.j2
bootstrap_py/templates/README.rst.j2
bootstrap_py/templates/__init__.py.j2
bootstrap_py/templates/pyproject.toml.j2
bootstrap_py/templates/sample.py.j2
bootstrap_py/templates/test_sample.py.j2
bootstrap_py/templates/tox.ini.j2
bootstrap_py/templates/.github/workflows/ci.yml.j2
bootstrap_py/templates/docs/source/CHANGELOG.rst.j2
bootstrap_py/templates/docs/source/index.rst.j2
bootstrap_py/templates/docs/source/modules/index.rst.j2
bootstrap_py/templates/utils/pre-commit.j2
bootstrap_py/tests/__init__.py
bootstrap_py/tests/stub.py
bootstrap_py/tests/test_classifiers.py
bootstrap_py/tests/test_commands.py
bootstrap_py/tests/test_control.py
bootstrap_py/tests/test_package.py
bootstrap_py/tests/test_pypi.py
bootstrap_py/tests/test_vcs.py
bootstrap_py/tests/data/badge.svg
bootstrap_py/tests/data/search_result
bootstrap_py-2.0.0.dist-info/LICENSE
bootstrap_py-2.0.0.dist-info/METADATA
bootstrap_py-2.0.0.dist-info/WHEEL
bootstrap_py-2.0.0.dist-info/entry_points.txt
bootstrap_py-2.0.0.dist-info/top_level.txt
bootstrap_py-2.0.0.dist-info/RECORD
