Metadata-Version: 2.1
Name: bootstrap-py
Version: 2.0.0
Summary: Template tool to easily generate your Python packages.
Author-email: Kouhei Maeda <mkouhei@palmtb.net>
License:                     GNU GENERAL PUBLIC LICENSE
Project-URL: Homepage, https://github.com/mkouhei/bootstrap-py
Classifier: Development Status :: 5 - Production/Stable
Classifier: Intended Audience :: Developers
Classifier: License :: OSI Approved :: GNU General Public License v3 or later (GPLv3+)
Classifier: Programming Language :: Python
Classifier: Programming Language :: Python :: 3
Classifier: Programming Language :: Python :: 3.9
Classifier: Programming Language :: Python :: 3.10
Classifier: Programming Language :: Python :: 3.11
Classifier: Programming Language :: Python :: Implementation :: CPython
Classifier: Topic :: Software Development
Classifier: Topic :: System :: Archiving :: Packaging
Classifier: Topic :: System :: Software Distribution
Requires-Python: >=3.9
Provides-Extra: test
Provides-Extra: doc
License-File: LICENSE
